AUTHORS
CHANGES.rst
LICENSE
MANIFEST.in
README.rst
conftest.py
setup.cfg
setup.py
docs/Makefile
docs/admin.rst
docs/conf.py
docs/index.rst
docs/intro.rst
docs/make.bat
docs/project.rst
docs/security.rst
docs/standards.rst
docs/user.rst
docs/_static/.gitignore
docs/_templates/.gitignore
docs/examples/bind9/named.conf
docs/examples/bind9/nsupdate.info-zonefile
docs/examples/nginx_gunicorn/gunicorn_start
docs/examples/nginx_gunicorn/nginx.conf
docs/examples/nginx_gunicorn/supervisor.conf
nsupdate/__init__.py
nsupdate/context_processors.py
nsupdate/urls.py
nsupdate/wsgi.py
nsupdate.egg-info/PKG-INFO
nsupdate.egg-info/SOURCES.txt
nsupdate.egg-info/dependency_links.txt
nsupdate.egg-info/not-zip-safe
nsupdate.egg-info/requires.txt
nsupdate.egg-info/top_level.txt
nsupdate/accounts/__init__.py
nsupdate/accounts/admin.py
nsupdate/accounts/forms.py
nsupdate/accounts/models.py
nsupdate/accounts/registration_form.py
nsupdate/accounts/urls.py
nsupdate/accounts/views.py
nsupdate/accounts/_tests/__init__.py
nsupdate/accounts/_tests/test_accounts.py
nsupdate/accounts/migrations/0001_initial.py
nsupdate/accounts/migrations/0002_auto_20141125_2325.py
nsupdate/accounts/migrations/__init__.py
nsupdate/accounts/templates/accounts/delete_user.html
nsupdate/accounts/templates/accounts/user_settings_account.html
nsupdate/accounts/templates/accounts/user_settings_base.html
nsupdate/accounts/templates/accounts/user_settings_profile.html
nsupdate/accounts/templates/registration/activate.html
nsupdate/accounts/templates/registration/activation_complete.html
nsupdate/accounts/templates/registration/activation_email.txt
nsupdate/accounts/templates/registration/activation_email_subject.txt
nsupdate/accounts/templates/registration/registration_base.html
nsupdate/accounts/templates/registration/registration_closed.html
nsupdate/accounts/templates/registration/registration_complete.html
nsupdate/accounts/templates/registration/registration_form.html
nsupdate/api/__init__.py
nsupdate/api/models.py
nsupdate/api/views.py
nsupdate/api/_tests/__init__.py
nsupdate/api/_tests/test_api.py
nsupdate/api/migrations/__init__.py
nsupdate/locale/de/LC_MESSAGES/django.mo
