Metadata-Version: 1.1
Name: nsupdate
Version: 0.12.0
Summary: A dynamic DNS update service
Home-page: http://github.com/nsupdate-info/nsupdate.info/
Author: The nsupdate.info Team (see AUTHORS)
Author-email: info@nsupdate.info
License: BSD
Keywords: dyndns ddns dynamic dns django
Platform: any
Classifier: Development Status :: 5 - Production/Stable
Classifier: Environment :: Web Environment
Classifier: Framework :: Django
Classifier: License :: OSI Approved :: BSD License
Classifier: Operating System :: OS Independent
Classifier: Programming Language :: Python
Classifier: Programming Language :: Python :: 2
Classifier: Programming Language :: Python :: 2.7
Classifier: Programming Language :: Python :: 3
Classifier: Programming Language :: Python :: 3.4
Classifier: Programming Language :: Python :: 3.5
Classifier: Programming Language :: Python :: 3.6
Classifier: Programming Language :: Python :: 3.7
Classifier: Topic :: Internet :: Name Service (DNS)
